odoo/addons/contract_termination/README.rst
odoo/addons/contract_termination/__init__.py
odoo/addons/contract_termination/__manifest__.py
odoo/addons/contract_termination/i18n/contract_termination.pot
odoo/addons/contract_termination/i18n/fr.po
odoo/addons/contract_termination/i18n/it.po
odoo/addons/contract_termination/i18n/nl.po
odoo/addons/contract_termination/i18n/pt_BR.po
odoo/addons/contract_termination/i18n/sv.po
odoo/addons/contract_termination/i18n/tr.po
odoo/addons/contract_termination/models/__init__.py
odoo/addons/contract_termination/models/contract_contract.py
odoo/addons/contract_termination/models/contract_line.py
odoo/addons/contract_termination/models/contract_terminate_reason.py
odoo/addons/contract_termination/readme/CONFIGURE.md
odoo/addons/contract_termination/readme/CONTRIBUTORS.md
odoo/addons/contract_termination/readme/DESCRIPTION.md
odoo/addons/contract_termination/readme/USAGE.md
odoo/addons/contract_termination/security/contract_terminate_reason.xml
odoo/addons/contract_termination/security/groups.xml
odoo/addons/contract_termination/security/ir.model.access.csv
odoo/addons/contract_termination/static/description/icon.png
odoo/addons/contract_termination/static/description/index.html
odoo/addons/contract_termination/tests/__init__.py
odoo/addons/contract_termination/tests/test_contract.py
odoo/addons/contract_termination/views/contract_contract.xml
odoo/addons/contract_termination/views/contract_terminate_reason.xml
odoo/addons/contract_termination/wizards/__init__.py
odoo/addons/contract_termination/wizards/contract_contract_terminate.py
odoo/addons/contract_termination/wizards/contract_contract_terminate.xml
odoo_addon_contract_termination-18.0.1.0.0.13.dist-info/METADATA
odoo_addon_contract_termination-18.0.1.0.0.13.dist-info/WHEEL
odoo_addon_contract_termination-18.0.1.0.0.13.dist-info/top_level.txt
odoo_addon_contract_termination-18.0.1.0.0.13.dist-info/RECORD
