Metadata-Version: 2.1
Name: odoo-addon-contract_termination
Version: 18.0.1.0.0.13
Requires-Python: >=3.10
Requires-Dist: odoo-addon-contract_line_successor==18.0.*
Requires-Dist: odoo==18.0.*
Summary: contract_termination
Home-page: https://github.com/OCA/contract
License: AGPL-3
Author: ACSONE SA/NV,Odoo Community Association (OCA)
Author-email: support@odoo-community.org
Classifier: Programming Language :: Python
Classifier: Framework :: Odoo
Classifier: Framework :: Odoo :: 18.0
Classifier: License :: OSI Approved :: GNU Affero General Public License v3
